aiobml/__init__.py
aiobml/client.py
aiobml/core/__init__.py
aiobml/core/errors.py
aiobml/core/http.py
aiobml-1.0.4.dist-info/LICENSE
aiobml-1.0.4.dist-info/METADATA
aiobml-1.0.4.dist-info/WHEEL
aiobml-1.0.4.dist-info/top_level.txt
aiobml-1.0.4.dist-info/RECORD
