Metadata-Version: 2.1
Name: aiobml
Version: 1.0.4
Summary: Asynchronous Python wrapper around Bank of Maldives (BML) API
Home-page: https://github.com/quillfires/aioBML
Author: Fayaz (Quill)
Author-email: fayaz.quill@gmail.com
Maintainer: quill <fayaz.quill@gmail.com>
Maintainer-email: fayaz.quill@gmail.com
License: MIT
Platform: UNKNOWN
Classifier: Development Status :: 5 - Production/Stable
Classifier: Environment :: Console
Classifier: Framework :: AsyncIO
Classifier: Intended Audience :: Developers
Classifier: Intended Audience :: System Administrators
Classifier: License :: OSI Approved :: MIT License
Classifier: Programming Language :: Python :: 3.9
Classifier: Programming Language :: Python :: 3.8
Classifier: Programming Language :: Python :: 3.7
Classifier: Topic :: Software Development :: Libraries :: Application Frameworks
Requires-Dist: aiohttp (>=3.6)
